vulnstick/__init__.py
vulnstick/arrange.py
vulnstick/artifact.py
vulnstick/capture.py
vulnstick/cli/__init__.py
vulnstick/cli/cli.py
vulnstick/cli/config.py
vulnstick/cli/display.py
vulnstick/cli/explore/__init__.py
vulnstick/cli/explore/image_labels/__init__.py
vulnstick/cli/explore/image_labels/cve_provider.py
vulnstick/cli/explore/image_labels/display_pane.py
vulnstick/cli/explore/image_labels/edit_note_dialog.py
vulnstick/cli/explore/image_labels/history.py
vulnstick/cli/explore/image_labels/label_json_editor_dialog.py
vulnstick/cli/explore/image_labels/label_manager.py
vulnstick/cli/explore/image_labels/label_margin.py
vulnstick/cli/explore/image_labels/label_selection_pane.py
vulnstick/cli/explore/image_labels/result_selection_pane.py
vulnstick/cli/explore/image_labels/text_area.py
vulnstick/cli/explore/image_labels/text_dialog.py
vulnstick/cli/explore/result.py
vulnstick/cli/label.py
vulnstick/cli/result.py
vulnstick/comparison.py
vulnstick/label.py
vulnstick/store/__init__.py
vulnstick/store/config.py
vulnstick/store/image_lineage.py
vulnstick/store/label_stats.py
vulnstick/store/labels.py
vulnstick/store/naming.py
vulnstick/store/result_set.py
vulnstick/store/scan_result.py
vulnstick/store/tool.py
vulnstick/tool/__init__.py
vulnstick/tool/grype.py
vulnstick/tool/plugin.py
vulnstick/tool/sbom_generator.py
vulnstick/tool/syft.py
vulnstick/tool/vulnerability_scanner.py
vulnstick/utils/__init__.py
vulnstick/utils/github.py
vulnstick/utils/grype_db.py
vulnstick-0.9.2.dist-info/LICENSE
vulnstick-0.9.2.dist-info/METADATA
vulnstick-0.9.2.dist-info/WHEEL
vulnstick-0.9.2.dist-info/entry_points.txt
vulnstick-0.9.2.dist-info/RECORD
